kudet_arac_degerleme/__init__.py
kudet_arac_degerleme/main.py
kudet_arac_degerleme/model_utils.py
kudet_arac_degerleme-0.1.0.dist-info/METADATA
kudet_arac_degerleme-0.1.0.dist-info/WHEEL
kudet_arac_degerleme-0.1.0.dist-info/top_level.txt
kudet_arac_degerleme-0.1.0.dist-info/RECORD
