Metadata-Version: 2.1
Name: kudet-arac-degerleme
Version: 0.1.0
Summary: Makine öğrenmesiyle ikinci el araç fiyat tahmini
Author: kudetx
Requires-Python: >=3.6
Requires-Dist: scikit-learn
Requires-Dist: pandas
Requires-Dist: numpy
